RegisterFile.sv
//Optimized for SystemVerilog
//Register file...

module RegisterFile(
    input logic [4:0] readRegister1, readRegister2, writeRegister,
    input logic regWrite,
    input logic Clk,
    input logic [63:0] writeData,
    output logic [63:0] BusA, BusB
    );

    //because Registers within Register File are neither outputs nor
    //inputs, they are labeled as "logic"

    logic [63:0] regs[31:0]; //32 registers, each 64-bits wide.

    //always_comb --> combinational logic
    //whenever inputs change, recompute outputs immediately

    //always_ff --> sequential logic / flip-flops
    //used for state machines, pipeline registers, registers
    //only update on rising edge of clock (sequential logic)

    always_ff @(negedge Clk) begin //negative edge of Clk signal
    //negedge to avoid read/write conflict in a single cycle.
        if(regWrite && (writeRegister != 5'd31)) begin //regWrite signal & writeRegister is not the zero register
         //Write data into selected register
         regs[writeRegister] <= writeData;
         //store writeData into register selected by writeRegister
        end
    end

    //Asynchronous read port A & port B
    always_comb begin
        if(readRegister1 == 5'd31)
            BusA=64'd0;
        else
            BusA=regs[readRegister1];
    end

    always_comb begin
        if(readRegister2 == 5'd31)
            BusB=64'd0;
        else
            BusB=regs[readRegister2];
    end
endmodule

RegisterFile_testbench.sv
//optimize for systemVerilog
`timescale 1ns/1ps

module RegisterFile_testbench;
    //testbench logic signals
    logic [4:0] readRegister1, readRegister2, writeRegister;
    logic regWrite;
    logic Clk;
    logic [63:0] writeData;
    logic [63:0] BusA, BusB;

    int passed;
    int num_tests;

    //Instatiate module
    RegisterFile uut (
        .readRegister1(readRegister1),
        .readRegister2(readRegister2),
        .writeRegister(writeRegister),
        .regWrite(regWrite),
        .Clk(Clk),
        .writeData(writeData),
        .BusA(BusA),
        .BusB(BusB)
    );

    //Generating waveform file (using surfer instead of GTK)
    initial begin
        $dumpfile("RegisterFileTest.vcd");
        $dumpvars(0, RegisterFile_testbench);
    end

    //Clock generation
    initial begin
        Clk = 1'b1;
        forever #20 Clk = ~Clk;
    end

    //Task to determine if each individual test case passed or failed.
    task automatic passTest(
        input logic [127:0] actualOut,
        input logic [127:0] expectedOut,
        input string testName
    );
        begin
            if(actualOut==expectedOut) begin
                $display("%s passed", testName); //systemVerilog syntax (%)
                passed++;
            end
            else begin
                $display("%s failed: got %x, expected %x",
                testName, actualOut, expectedOut);
            end
        end
    endtask


    //Task to determine how many test cases passed
    task automatic allPassed(
        input int passedCount,
        input int totalTests
    );
        begin
            if (passedCount == totalTests)
                $display("All tests passed");
            else
                $display("Some tests failed: %0d/%0d passed",
                         passedCount, totalTests);
        end
    endtask


    //Starting main test sequence


    initial begin

        // Initialize inputs
        readRegister1  = 5'd31;
        readRegister2  = 5'd31;
        writeRegister  = 5'd0;
        regWrite       = 1'b0;
        writeData      = 64'd0;
        passed         = 0;
        num_tests      = 6;

        // Register 31 Tests
        #40;
        passTest({BusA, BusB}, {64'd0, 64'd0}, "Read zero register on BusA and BusB");

        // Write to register 5
        {readRegister1, readRegister2, writeRegister, regWrite, writeData} =
            {5'd31, 5'd31, 5'd5, 1'b1, 64'h123456789ABCDEF0};
        #40;

        // Reading Register 5 thru BusA
        {readRegister1, readRegister2, writeRegister, regWrite, writeData} =
            {5'd5, 5'd31, 5'd5, 1'b0, 64'h123456789ABCDEF0};
        #40;
        // Testing thru pre-written task
        passTest({BusA, BusB}, {64'h123456789ABCDEF0, 64'd0}, "Write/read register 5 on BusA");




        // Read the same register from BusB
        {readRegister1, readRegister2, writeRegister, regWrite, writeData} =
            {5'd31, 5'd5, 5'd5, 1'b0, 64'h123456789ABCDEF0};
        #40;
        passTest({BusA, BusB}, {64'd0, 64'h123456789ABCDEF0}, "Read register 5 on BusB");




        // Write to register 10, then read both register 5 and register 10
        {readRegister1, readRegister2, writeRegister, regWrite, writeData} =
            {5'd31, 5'd31, 5'd10, 1'b1, 64'h0F0F0F0F0F0F0F0F};
        #40;

        {readRegister1, readRegister2, writeRegister, regWrite, writeData} =
            {5'd5, 5'd10, 5'd10, 1'b0, 64'h0F0F0F0F0F0F0F0F};
        #40;
        passTest({BusA, BusB}, {64'h123456789ABCDEF0, 64'h0F0F0F0F0F0F0F0F}, "Read registers 5 and 10");




        // Register 31 should ignore writes and still read as zero
        {readRegister1, readRegister2, writeRegister, regWrite, writeData} =
            {5'd31, 5'd10, 5'd31, 1'b1, 64'hFFFFFFFFFFFFFFFF};
        #40;

        {readRegister1, readRegister2, writeRegister, regWrite, writeData} =
            {5'd31, 5'd10, 5'd31, 1'b0, 64'hFFFFFFFFFFFFFFFF};
        #40;
        passTest({BusA, BusB}, {64'd0, 64'h0F0F0F0F0F0F0F0F}, "Register 31 write ignored");




        //USER ADDED TESTCASES...
        //Write to Register 12 & 22, then read both Register 12 & 22
        {readRegister1, readRegister2, writeRegister, regWrite, writeData} = 
            {5'd31, 5'd31, 5'd12, 1'b1, 64'h000000000000000A};
        #40;

        {readRegister1, readRegister2, writeRegister, regWrite, writeData} = 
            {5'd31, 5'd31, 5'd22, 1'b1, 64'h000000000000000B};
        #40;
        
        //reading the register is seen to verify if the write actually worked.
        {readRegister1, readRegister2, writeRegister, regWrite, writeData} = 
            {5'd12, 5'd22, 5'd31, 1'b0, 64'h0000000000000000};
        #40;
        passTest({BusA, BusB}, {64'h000000000000000A, 64'h000000000000000B}, "Read Register 12 & 22");
        #40;

        // Print final summary
        allPassed(passed, num_tests);

        // End simulation (indicated simulation termination)
        $finish;

    end

endmodule

//NOTE: ADD MORE TO THIS TESTBENCH, WRITE UNIQUE CASES.

waveforms & object directories/RegisterFile/RegisterFileTest.vcd
$version Generated by VerilatedVcd $end
$timescale 1ps $end
 $scope module RegisterFile_testbench $end
  $var wire 5 " readRegister1 [4:0] $end
  $var wire 5 # readRegister2 [4:0] $end
  $var wire 5 $ writeRegister [4:0] $end
  $var wire 1 % regWrite $end
  $var wire 1 * Clk $end
  $var wire 64 & writeData [63:0] $end
  $var wire 64 + BusA [63:0] $end
  $var wire 64 - BusB [63:0] $end
  $var wire 32 ( passed [31:0] $end
  $var wire 32 ) num_tests [31:0] $end
  $scope module uut $end
   $var wire 5 " readRegister1 [4:0] $end
   $var wire 5 # readRegister2 [4:0] $end
   $var wire 5 $ writeRegister [4:0] $end
   $var wire 1 % regWrite $end
   $var wire 1 * Clk $end
   $var wire 64 & writeData [63:0] $end
   $var wire 64 + BusA [63:0] $end
   $var wire 64 - BusB [63:0] $end
   $var wire 64 / regs[31] [63:0] $end
   $var wire 64 1 regs[30] [63:0] $end
   $var wire 64 3 regs[29] [63:0] $end
   $var wire 64 5 regs[28] [63:0] $end
   $var wire 64 7 regs[27] [63:0] $end
   $var wire 64 9 regs[26] [63:0] $end
   $var wire 64 ; regs[25] [63:0] $end
   $var wire 64 = regs[24] [63:0] $end
   $var wire 64 ? regs[23] [63:0] $end
   $var wire 64 A regs[22] [63:0] $end
   $var wire 64 C regs[21] [63:0] $end
   $var wire 64 E regs[20] [63:0] $end
   $var wire 64 G regs[19] [63:0] $end
   $var wire 64 I regs[18] [63:0] $end
   $var wire 64 K regs[17] [63:0] $end
   $var wire 64 M regs[16] [63:0] $end
   $var wire 64 O regs[15] [63:0] $end
   $var wire 64 Q regs[14] [63:0] $end
   $var wire 64 S regs[13] [63:0] $end
   $var wire 64 U regs[12] [63:0] $end
   $var wire 64 W regs[11] [63:0] $end
   $var wire 64 Y regs[10] [63:0] $end
   $var wire 64 [ regs[9] [63:0] $end
   $var wire 64 ] regs[8] [63:0] $end
   $var wire 64 _ regs[7] [63:0] $end
   $var wire 64 a regs[6] [63:0] $end
   $var wire 64 c regs[5] [63:0] $end
   $var wire 64 e regs[4] [63:0] $end
   $var wire 64 g regs[3] [63:0] $end
   $var wire 64 i regs[2] [63:0] $end
   $var wire 64 k regs[1] [63:0] $end
   $var wire 64 m regs[0] [63:0] $end
  $upscope $end
 $upscope $end
$enddefinitions $end


#0
b11111 "
b11111 #
b00000 $
0%
b0000000000000000000000000000000000000000000000000000000000000000 &
b00000000000000000000000000000000 (
b00000000000000000000000000000110 )
1*
b0000000000000000000000000000000000000000000000000000000000000000 +
b0000000000000000000000000000000000000000000000000000000000000000 -
b0000000000000000000000000000000000000000000000000000000000000000 /
b0000000000000000000000000000000000000000000000000000000000000000 1
b0000000000000000000000000000000000000000000000000000000000000000 3
b0000000000000000000000000000000000000000000000000000000000000000 5
b0000000000000000000000000000000000000000000000000000000000000000 7
b0000000000000000000000000000000000000000000000000000000000000000 9
b0000000000000000000000000000000000000000000000000000000000000000 ;
b0000000000000000000000000000000000000000000000000000000000000000 =
b0000000000000000000000000000000000000000000000000000000000000000 ?
b0000000000000000000000000000000000000000000000000000000000000000 A
b0000000000000000000000000000000000000000000000000000000000000000 C
b0000000000000000000000000000000000000000000000000000000000000000 E
b0000000000000000000000000000000000000000000000000000000000000000 G
b0000000000000000000000000000000000000000000000000000000000000000 I
b0000000000000000000000000000000000000000000000000000000000000000 K
b0000000000000000000000000000000000000000000000000000000000000000 M
b0000000000000000000000000000000000000000000000000000000000000000 O
b0000000000000000000000000000000000000000000000000000000000000000 Q
b0000000000000000000000000000000000000000000000000000000000000000 S
b0000000000000000000000000000000000000000000000000000000000000000 U
b0000000000000000000000000000000000000000000000000000000000000000 W
b0000000000000000000000000000000000000000000000000000000000000000 Y
b0000000000000000000000000000000000000000000000000000000000000000 [
b0000000000000000000000000000000000000000000000000000000000000000 ]
b0000000000000000000000000000000000000000000000000000000000000000 _
b0000000000000000000000000000000000000000000000000000000000000000 a
b0000000000000000000000000000000000000000000000000000000000000000 c
b0000000000000000000000000000000000000000000000000000000000000000 e
b0000000000000000000000000000000000000000000000000000000000000000 g
b0000000000000000000000000000000000000000000000000000000000000000 i
b0000000000000000000000000000000000000000000000000000000000000000 k
b0000000000000000000000000000000000000000000000000000000000000000 m
#20000
0*
#40000
b00101 $
1%
b0001001000110100010101100111100010011010101111001101111011110000 &
b00000000000000000000000000000001 (
1*
#60000
0*
b0001001000110100010101100111100010011010101111001101111011110000 c
#80000
b00101 "
0%
1*
b0001001000110100010101100111100010011010101111001101111011110000 +
#100000
0*
#120000
b11111 "
b00101 #
b00000000000000000000000000000010 (
1*
b0000000000000000000000000000000000000000000000000000000000000000 +
b0001001000110100010101100111100010011010101111001101111011110000 -
#140000
0*
#160000
b11111 #
b01010 $
1%
b0000111100001111000011110000111100001111000011110000111100001111 &
b00000000000000000000000000000011 (
1*
b0000000000000000000000000000000000000000000000000000000000000000 -
#180000
0*
b0000111100001111000011110000111100001111000011110000111100001111 Y
#200000
b00101 "
b01010 #
0%
1*
b0001001000110100010101100111100010011010101111001101111011110000 +
b0000111100001111000011110000111100001111000011110000111100001111 -
#220000
0*
#240000
b11111 "
b11111 $
1%
b1111111111111111111111111111111111111111111111111111111111111111 &
b00000000000000000000000000000100 (
1*
b0000000000000000000000000000000000000000000000000000000000000000 +
#260000
0*
#280000
0%
1*
#300000
0*
#320000
b11111 #
b01100 $
1%
b0000000000000000000000000000000000000000000000000000000000001010 &
b00000000000000000000000000000101 (
1*
b0000000000000000000000000000000000000000000000000000000000000000 -
#340000
0*
b0000000000000000000000000000000000000000000000000000000000001010 U
#360000
b10110 $
b0000000000000000000000000000000000000000000000000000000000001011 &
1*
#380000
0*
b0000000000000000000000000000000000000000000000000000000000001011 A
#400000
b01100 "
b10110 #
b11111 $
0%
b0000000000000000000000000000000000000000000000000000000000000000 &
1*
b0000000000000000000000000000000000000000000000000000000000001010 +
b0000000000000000000000000000000000000000000000000000000000001011 -
#420000
0*
#440000
b00000000000000000000000000000110 (
1*
