rtl/signExtender.sv
//optimized code for SystemVerilog
//Development of Sign-Extend module

//Recall SignOp value
//00 = I-type
//01 = D-type
//10 = B-type
//11 = CB-type

module signExtender(
    input logic [25:0] Instr,
    input logic [1:0] SignOp,
    output logic [63:0] BusImm
    );

//Sign-Extend is used in specific cases, and not all input bits are filled
//Assigne BusImm (output) using Verilog If-Else Block
    assign BusImm = 
    //i-type
    (SignOp==2'b00) ? {{52'b0}, Instr[21:10]}: //12 immediate bits + 52 bits
    //d-type
    (SignOp==2'b01) ? {{55{Instr[20]}}, Instr[20:12]}: //sign-extend
    //b-type
    (SignOp==2'b10) ? {{38{Instr[25]}}, Instr[25:0]}: //sign extend

    //cb-type (acting as default case)
    {{45{Instr[23]}}, Instr[23:5]};

endmodule

signExtender_testbench.sv
//optimize for systemVerilog
`timescale 1ns/1ps

module signExtender_testbench;
    //testbench logic signals
    //replace reg&wire with logic
    logic [25:0] Instr;
    logic [1:0] SignOp;
    logic [63:0] BusImm;

    int passed;
    int num_tests;

    //Instatiate module
    signExtender uut (
        .Instr(Instr),
        .SignOp(SignOp),
        .BusImm(BusImm)
    );

    //Generating waveform file (using surfer instead of GTK)
    initial begin
        $dumpfile("signExtenderTest.vcd");
        $dumpvars(0, signExtender_testbench);
    end

    //Task to determine if each individual test case passed or failed.
    task automatic passTest(
        input logic [63:0] actualOut,
        input logic [63:0] expectedOut,
        input string testName
    );
        begin
            if(actualOut==expectedOut) begin
                $display("%s passed", testName); //systemVerilog syntax (%)
                passed++;
            end
            else begin
                $display("%s failed: got %x, expected %x",
                testName, actualOut, expectedOut);
            end
        end
    endtask

    //Task to determine how many test cases passed
    task automatic allPassed(
        input int passedCount,
        input int totalTests
    );
        begin
            if (passedCount == totalTests)
                $display("All tests passed");
            else
                $display("Some tests failed: %0d/%0d passed",
                         passedCount, totalTests);
        end
    endtask

    //Starting main test sequence
    initial begin

        // Initialize inputs
        Instr     = 26'd0;
        SignOp    = 2'd0;
        passed    = 0;
        num_tests = 12;

        // I-type Tests: zero-extend Instr[21:10]
        {Instr, SignOp} = {26'h0000000, 2'b00};
        #40;
        passTest(BusImm, 64'h0000000000000000, "I-type immediate 0x000");

        {Instr, SignOp} = {26'h0000400, 2'b00};
        #40;
        passTest(BusImm, 64'h0000000000000001, "I-type immediate 0x001");

        {Instr, SignOp} = {26'h03FFC00, 2'b00};
        #40;
        passTest(BusImm, 64'h0000000000000FFF, "I-type immediate 0xFFF");

        // D-type Tests: sign-extend Instr[20:12]
        {Instr, SignOp} = {26'h0000000, 2'b01};
        #40;
        passTest(BusImm, 64'h0000000000000000, "D-type immediate 0x000");

        {Instr, SignOp} = {26'h0100000, 2'b01};
        #40;
        passTest(BusImm, 64'hFFFFFFFFFFFFFF00, "D-type negative immediate 0x100");

        {Instr, SignOp} = {26'h00FF000, 2'b01};
        #40;
        passTest(BusImm, 64'h00000000000000FF, "D-type positive immediate 0x0FF");

        // B-type Tests: sign-extend Instr[25:0]
        {Instr, SignOp} = {26'h0000000, 2'b10};
        #40;
        passTest(BusImm, 64'h0000000000000000, "B-type immediate 0x0000000");

        {Instr, SignOp} = {26'h2000000, 2'b10};
        #40;
        passTest(BusImm, 64'hFFFFFFFFFE000000, "B-type negative immediate 0x2000000");

        {Instr, SignOp} = {26'h1FFFFFF, 2'b10};
        #40;
        passTest(BusImm, 64'h0000000001FFFFFF, "B-type positive immediate 0x1FFFFFF");

        // CB-type Tests: sign-extend Instr[23:5]
        {Instr, SignOp} = {26'h0000000, 2'b11};
        #40;
        passTest(BusImm, 64'h0000000000000000, "CB-type immediate 0x00000");

        {Instr, SignOp} = {26'h0800000, 2'b11};
        #40;
        passTest(BusImm, 64'hFFFFFFFFFFFC0000, "CB-type negative immediate 0x40000");

        {Instr, SignOp} = {26'h07FFFE0, 2'b11};
        #40;
        passTest(BusImm, 64'h000000000003FFFF, "CB-type positive immediate 0x3FFFF");

        // Print final summary
        allPassed(passed, num_tests);

        // End simulation (indicated simulation termination)
        $finish;

    end

endmodule

waveforms & object directories/signExtender/signExtenderTest.vcd
$version Generated by VerilatedVcd $end
$timescale 1ps $end
 $scope module signExtender_testbench $end
  $var wire 26 " Instr [25:0] $end
  $var wire 2 # SignOp [1:0] $end
  $var wire 64 $ BusImm [63:0] $end
  $var wire 32 & passed [31:0] $end
  $var wire 32 ' num_tests [31:0] $end
  $scope module uut $end
   $var wire 26 " Instr [25:0] $end
   $var wire 2 # SignOp [1:0] $end
   $var wire 64 $ BusImm [63:0] $end
  $upscope $end
 $upscope $end
$enddefinitions $end


#0
b00000000000000000000000000 "
b00 #
b0000000000000000000000000000000000000000000000000000000000000000 $
b00000000000000000000000000000000 &
b00000000000000000000000000001100 '
#40000
b00000000000000010000000000 "
b0000000000000000000000000000000000000000000000000000000000000001 $
b00000000000000000000000000000001 &
#80000
b00001111111111110000000000 "
b0000000000000000000000000000000000000000000000000000111111111111 $
b00000000000000000000000000000010 &
#120000
b00000000000000000000000000 "
b01 #
b0000000000000000000000000000000000000000000000000000000000000000 $
b00000000000000000000000000000011 &
#160000
b00000100000000000000000000 "
b1111111111111111111111111111111111111111111111111111111100000000 $
b00000000000000000000000000000100 &
#200000
b00000011111111000000000000 "
b0000000000000000000000000000000000000000000000000000000011111111 $
b00000000000000000000000000000101 &
#240000
b00000000000000000000000000 "
b10 #
b0000000000000000000000000000000000000000000000000000000000000000 $
b00000000000000000000000000000110 &
#280000
b10000000000000000000000000 "
b1111111111111111111111111111111111111110000000000000000000000000 $
b00000000000000000000000000000111 &
#320000
b01111111111111111111111111 "
b0000000000000000000000000000000000000001111111111111111111111111 $
b00000000000000000000000000001000 &
#360000
b00000000000000000000000000 "
b11 #
b0000000000000000000000000000000000000000000000000000000000000000 $
b00000000000000000000000000001001 &
#400000
b00100000000000000000000000 "
b1111111111111111111111111111111111111111111111000000000000000000 $
b00000000000000000000000000001010 &
#440000
b00011111111111111111100000 "
b0000000000000000000000000000000000000000000000111111111111111111 $
b00000000000000000000000000001011 &
#480000
b00000000000000000000000000001100 &
