ALU.sv
//optimized code for SystemVerilog
//ALU module in 5-stage pipeline processor...

//two 64-bit inputs, 4-bit ALU operation, output is zero bit & busW
module ALU(
   output logic [63:0] BusW, //output, 
   input logic [63:0] BusA, 
   input logic [63:0] BusB,
   input logic [3:0] ALUCtrl, //control signal,
   output logic Zero //high when BusW=0
   );

   //ALU operation encoding...
   //localparam will keep constants local to this specific module.
   localparam logic [3:0]
      AND = 4'b0000, //bitwise and
      OR = 4'b0001, //bitwise or
      ADD = 4'b0010, //bitwise ADD
      SUB = 4'b0110, //bitwise SUB
      PASSB = 4'b0111; //pass BusB directly to output
   
   //combinational ALU logic
   //always_comb automatically builds sensitivity list...
   always_comb begin
      //select ALU operation based on ALUCtrl.
      case(ALUCtrl)
         AND:
            BusW=BusA&BusB;
         OR:
            BusW=BusA|BusB;
         ADD:
            BusW=BusA+BusB;
         SUB:
            BusW=BusA-BusB;
         PASSB:
            BusW=BusB;
         
         //ensure a default case
         default:
            BusW=64'd0;
      endcase
   end
   //assign output zero
   assign Zero = (BusW==64'd0);
endmodule

tb/ALU_testbench.sv
//optimize for systemVerilog
`timescale 1ns/1ps

module ALU_testbench;
    //testbench logic signals
    //replace reg&wire with logic
    logic [63:0] BusA, BusB;
    logic [3:0] ALUCtrl;
    logic [63:0] BusW;
    logic Zero;

    int passed;
    int num_tests;

    //Instatiate module
    ALU uut (
        .BusA(BusA),
        .BusB(BusB),
        .ALUCtrl(ALUCtrl),
        .BusW(BusW),
        .Zero(Zero)
    );

    //Generating waveform file (using surfer instead of GTK)
    initial begin
        $dumpfile("ALUTest.vcd");
        $dumpvars(0, ALUTest);
    end


    //Task to determine if each individual test case passed or failed.
    task automatic passTest(
        input logic [64:0] actualOut,
        input logic [64:0] expectedOut,
        input string testName
    );
        begin
            if(actualOut==expectedOut) begin
                $display("%s passed", testName); //systemVerilog syntax (%)
                passed++;
            end
            else begin
                $display("%s failed: got %x, expected %x",
                testName, actualOut, expectedOut);
            end
        end
    endtask


    //Task to determine how many test cases passed
    task automatic allPassed(
        input int passedCount,
        input int totalTests
    );
        begin
            if (passedCount == totalTests)
                $display("All tests passed");
            else
                $display("Some tests failed: %0d/%0d passed",
                         passedCount, totalTests);
        end
    endtask


    //Starting main test sequence


    initial begin

        // Initialize inputs
        BusA     = 64'd0;
        BusB     = 64'd0;
        ALUCtrl  = 4'd0;
        passed   = 0;
        num_tests = 16;

        // ADD example test
        {BusA, BusB, ALUCtrl} = {64'h1234, 64'hABCD0000, 4'h2}; //re-defining inputs for each test-case scenario
        #40; //ALU needs simulation time to recompute outputs, propagate and update signals.

        //running the inputs through the task
        passTest({Zero, BusW}, 65'h0ABCD1234, "ADD 0x1234, 0xABCD0000");




        // AND Tests
        {BusA, BusB, ALUCtrl} = {64'hFFFFFFFFFFFFFFFF, 64'h1234123412341234, 4'h0};
        #40;
        passTest({Zero, BusW}, 65'h01234123412341234, "AND all ones, 0x1234123412341234");


        {BusA, BusB, ALUCtrl} = {64'h0, 64'hAAAADDDDAAAADDDD, 4'h0};
        #40;
        passTest({Zero, BusW}, 65'h10000000000000000, "AND 0x0, 0xAAAADDDDAAAADDDD");

        {BusA, BusB, ALUCtrl} = {64'hF0F0F0F0F0F0F0F0, 64'hA1B2C3D4A1B2C3D4, 4'h0};
        #40;
        passTest({Zero, BusW}, 65'h0A0B0C0D0A0B0C0D0, "AND patterned inputs");

        // OR Tests
        {BusA, BusB, ALUCtrl} = {64'hFFFFFFFFFFFFFFFF, 64'h5678567856785678, 4'h1};
        #40;
        passTest({Zero, BusW}, 65'h0FFFFFFFFFFFFFFFF, "OR all ones, 0x5678567856785678");

        {BusA, BusB, ALUCtrl} = {64'h0, 64'h0, 4'h1};
        #40;
        passTest({Zero, BusW}, 65'h10000000000000000, "OR 0x0, 0x0");

        {BusA, BusB, ALUCtrl} = {64'hF0F0F0F0F0F0F0F0, 64'hABCD1234ABCD1234, 4'h1};
        #40;
        passTest({Zero, BusW}, 65'h0FBFDF2F4FBFDF2F4, "OR patterned inputs");


        // ADD Tests

        {BusA, BusB, ALUCtrl} = {64'h0, 64'h0, 4'h2};
        #40;
        passTest({Zero, BusW}, 65'h10000000000000000, "ADD 0x0, 0x0");

        {BusA, BusB, ALUCtrl} = {64'hF, 64'h1, 4'h2};
        #40;
        passTest({Zero, BusW}, 65'h00000000000000010, "ADD 0xF, 0x1");

        {BusA, BusB, ALUCtrl} = {64'h12341230, 64'h4, 4'h2};
        #40;
        passTest({Zero, BusW}, 65'h00000000012341234, "ADD 0x12341230, 0x4");


        // SUB Tests


        {BusA, BusB, ALUCtrl} = {64'h0, 64'h0, 4'h6};
        #40;
        passTest({Zero, BusW}, 65'h10000000000000000, "SUB 0x0, 0x0");

        {BusA, BusB, ALUCtrl} = {64'h10, 64'h1, 4'h6};
        #40;
        passTest({Zero, BusW}, 65'h0000000000000000F, "SUB 0x10, 0x1");

        {BusA, BusB, ALUCtrl} = {64'hAAAABBBB, 64'h2, 4'h6};
        #40;
        passTest({Zero, BusW}, 65'h000000000AAAABBB9, "SUB 0xAAAABBBB, 0x2");


        // PassB Tests


        {BusA, BusB, ALUCtrl} = {64'hAAAAAAAAAAAAAAAA, 64'h0, 4'h7};
        #40;
        passTest({Zero, BusW}, 65'h10000000000000000, "PassB with BusB = 0");

        {BusA, BusB, ALUCtrl} = {64'h0, 64'hFFFFFFFFFFFFFFFF, 4'h7};
        #40;
        passTest({Zero, BusW}, 65'h0FFFFFFFFFFFFFFFF, "PassB with BusB = all ones");

        {BusA, BusB, ALUCtrl} = {64'h1357135724682468, 64'hAABBAABBAABBAABB, 4'h7};
        #40;
        passTest({Zero, BusW}, 65'h0AABBAABBAABBAABB, "PassB patterned input");

        // Print final summary
        allPassed(passed, num_tests);

        // End simulation (indicated simulation termination)
        $finish;

    end

endmodule

waveforms & object directories/ALU/ALUTest.vcd
$version Generated by VerilatedVcd $end
$timescale 1ps $end
 $scope module ALU_testbench $end
  $var wire 64 " BusA [63:0] $end
  $var wire 64 $ BusB [63:0] $end
  $var wire 4 & ALUCtrl [3:0] $end
  $var wire 64 ' BusW [63:0] $end
  $var wire 1 ) Zero $end
  $var wire 32 * passed [31:0] $end
  $var wire 32 + num_tests [31:0] $end
  $scope module uut $end
   $var wire 64 ' BusW [63:0] $end
   $var wire 64 " BusA [63:0] $end
   $var wire 64 $ BusB [63:0] $end
   $var wire 4 & ALUCtrl [3:0] $end
   $var wire 1 ) Zero $end
   $var wire 4 , AND [3:0] $end
   $var wire 4 - OR [3:0] $end
   $var wire 4 . ADD [3:0] $end
   $var wire 4 / SUB [3:0] $end
   $var wire 4 0 PASSB [3:0] $end
  $upscope $end
 $upscope $end
$enddefinitions $end


#0
b0000000000000000000000000000000000000000000000000001001000110100 "
b0000000000000000000000000000000010101011110011010000000000000000 $
b0010 &
b0000000000000000000000000000000010101011110011010001001000110100 '
0)
b00000000000000000000000000000000 *
b00000000000000000000000000010000 +
b0000 ,
b0001 -
b0010 .
b0110 /
b0111 0
#40000
b1111111111111111111111111111111111111111111111111111111111111111 "
b0001001000110100000100100011010000010010001101000001001000110100 $
b0000 &
b0001001000110100000100100011010000010010001101000001001000110100 '
b00000000000000000000000000000001 *
#80000
b0000000000000000000000000000000000000000000000000000000000000000 "
b1010101010101010110111011101110110101010101010101101110111011101 $
b0000000000000000000000000000000000000000000000000000000000000000 '
1)
b00000000000000000000000000000010 *
#120000
b1111000011110000111100001111000011110000111100001111000011110000 "
b1010000110110010110000111101010010100001101100101100001111010100 $
b1010000010110000110000001101000010100000101100001100000011010000 '
0)
b00000000000000000000000000000011 *
#160000
b1111111111111111111111111111111111111111111111111111111111111111 "
b0101011001111000010101100111100001010110011110000101011001111000 $
b0001 &
b1111111111111111111111111111111111111111111111111111111111111111 '
b00000000000000000000000000000100 *
#200000
b0000000000000000000000000000000000000000000000000000000000000000 "
b0000000000000000000000000000000000000000000000000000000000000000 $
b0000000000000000000000000000000000000000000000000000000000000000 '
1)
b00000000000000000000000000000101 *
#240000
b1111000011110000111100001111000011110000111100001111000011110000 "
b1010101111001101000100100011010010101011110011010001001000110100 $
b1111101111111101111100101111010011111011111111011111001011110100 '
0)
b00000000000000000000000000000110 *
#280000
b0000000000000000000000000000000000000000000000000000000000000000 "
b0000000000000000000000000000000000000000000000000000000000000000 $
b0010 &
b0000000000000000000000000000000000000000000000000000000000000000 '
1)
b00000000000000000000000000000111 *
#320000
b0000000000000000000000000000000000000000000000000000000000001111 "
b0000000000000000000000000000000000000000000000000000000000000001 $
b0000000000000000000000000000000000000000000000000000000000010000 '
0)
b00000000000000000000000000001000 *
#360000
b0000000000000000000000000000000000010010001101000001001000110000 "
b0000000000000000000000000000000000000000000000000000000000000100 $
b0000000000000000000000000000000000010010001101000001001000110100 '
b00000000000000000000000000001001 *
#400000
b0000000000000000000000000000000000000000000000000000000000000000 "
b0000000000000000000000000000000000000000000000000000000000000000 $
b0110 &
b0000000000000000000000000000000000000000000000000000000000000000 '
1)
b00000000000000000000000000001010 *
#440000
b0000000000000000000000000000000000000000000000000000000000010000 "
b0000000000000000000000000000000000000000000000000000000000000001 $
b0000000000000000000000000000000000000000000000000000000000001111 '
0)
b00000000000000000000000000001011 *
#480000
b0000000000000000000000000000000010101010101010101011101110111011 "
b0000000000000000000000000000000000000000000000000000000000000010 $
b0000000000000000000000000000000010101010101010101011101110111001 '
b00000000000000000000000000001100 *
#520000
b1010101010101010101010101010101010101010101010101010101010101010 "
b0000000000000000000000000000000000000000000000000000000000000000 $
b0111 &
b0000000000000000000000000000000000000000000000000000000000000000 '
1)
b00000000000000000000000000001101 *
#560000
b0000000000000000000000000000000000000000000000000000000000000000 "
b1111111111111111111111111111111111111111111111111111111111111111 $
b1111111111111111111111111111111111111111111111111111111111111111 '
0)
b00000000000000000000000000001110 *
#600000
b0001001101010111000100110101011100100100011010000010010001101000 "
b1010101010111011101010101011101110101010101110111010101010111011 $
b1010101010111011101010101011101110101010101110111010101010111011 '
b00000000000000000000000000001111 *
#640000
b00000000000000000000000000010000 *
